graph_store/__init__.py
graph_store/base.py
graph_store/neo4j_store.py
memory/__init__.py
memory/entity_memory.py
memory/memory_base.py
memory/semantic_memory.py
memory/v1/__init__.py
memory/v1/semantic_memory_v1.py
simplememory-0.0.3.dist-info/LICENSE
simplememory-0.0.3.dist-info/METADATA
simplememory-0.0.3.dist-info/WHEEL
simplememory-0.0.3.dist-info/top_level.txt
simplememory-0.0.3.dist-info/RECORD
