Metadata-Version: 2.1
Name: simplememory
Version: 0.0.3
Summary: The framework for agent memory
Author-email: agent memory <agentmemorydefault@gmail.com>
Project-URL: Homepage, https://github.com/agencymemory/simplememory
Classifier: Programming Language :: Python :: 3
Classifier: License :: OSI Approved :: MIT License
Classifier: Operating System :: OS Independent
Requires-Python: >=3.10
License-File: LICENSE
Requires-Dist: pydantic ==2.7.4
Requires-Dist: openai ==1.34.0
Requires-Dist: langchain-openai ==0.1.8
Requires-Dist: python-dotenv ==1.0.1
Requires-Dist: pinecone-client ==4.1.1
Requires-Dist: neo4j ==5.21.0
Requires-Dist: langchain-experimental ==0.0.61
